facia_mcp/__init__.py
facia_mcp/client.py
facia_mcp/server.py
barie_facia_mcp-0.1.0.dist-info/METADATA
barie_facia_mcp-0.1.0.dist-info/WHEEL
barie_facia_mcp-0.1.0.dist-info/entry_points.txt
barie_facia_mcp-0.1.0.dist-info/RECORD
