Metadata-Version: 2.4
Name: barie-facia-mcp
Version: 0.1.0
Summary: Facia MCP Server for facial analysis (age estimation, deepfake detection, face match) via the Model Context Protocol
Author-email: Barie <support@barie.ai>
License: MIT
Keywords: deepfake,face,facia,liveness,mcp,model-context-protocol
Classifier: Development Status :: 4 - Beta
Classifier: Intended Audience :: Developers
Classifier: License :: OSI Approved :: MIT License
Classifier: Programming Language :: Python :: 3
Classifier: Programming Language :: Python :: 3.9
Classifier: Programming Language :: Python :: 3.10
Classifier: Programming Language :: Python :: 3.11
Classifier: Programming Language :: Python :: 3.12
Requires-Python: >=3.9
Requires-Dist: httpx>=0.25.0
Requires-Dist: mcp>=0.9.0
Requires-Dist: python-multipart>=0.0.6
Provides-Extra: dev
Requires-Dist: black>=23.0.0; extra == 'dev'
Requires-Dist: pytest>=7.0.0; extra == 'dev'
Requires-Dist: ruff>=0.1.0; extra == 'dev'
